sverilogpy_bind.cpython-39-darwin.so
sverilogpy/sverilog.cpp
sverilogpy/__init__.py
sverilogpy/py.typed
sverilogpy-0.0.0a2.dist-info/RECORD
sverilogpy-0.0.0a2.dist-info/LICENSE
sverilogpy-0.0.0a2.dist-info/WHEEL
sverilogpy-0.0.0a2.dist-info/top_level.txt
sverilogpy-0.0.0a2.dist-info/METADATA
